<profile>

<ReportVersion>
<Version>2023.1</Version>
</ReportVersion>

<UserAssignments>
<unit>ns</unit>
<ProductFamily>virtexuplus</ProductFamily>
<Part>xcvu11p-flga2577-1-e</Part>
<TopModelName>naive_findClustersHLS1_Pipeline_VITIS_LOOP_199_5_VITIS_LOOP_200_6</TopModelName>
<TargetClockPeriod>10.00</TargetClockPeriod>
<ClockUncertainty>2.70</ClockUncertainty>
<FlowTarget>vivado</FlowTarget>
</UserAssignments>

<PerformanceEstimates>
<PipelineType>no</PipelineType>
<SummaryOfTimingAnalysis>
<unit>ns</unit>
<EstimatedClockPeriod>3.179</EstimatedClockPeriod>
</SummaryOfTimingAnalysis>
<SummaryOfOverallLatency>
<unit>clock cycles</unit>
<Best-caseLatency>102</Best-caseLatency>
<Average-caseLatency>102</Average-caseLatency>
<Worst-caseLatency>102</Worst-caseLatency>
<Best-caseRealTimeLatency>1.020 us</Best-caseRealTimeLatency>
<Average-caseRealTimeLatency>1.020 us</Average-caseRealTimeLatency>
<Worst-caseRealTimeLatency>1.020 us</Worst-caseRealTimeLatency>
<Interval-min>102</Interval-min>
<Interval-max>102</Interval-max>
</SummaryOfOverallLatency>
<SummaryOfLoopLatency>
<VITIS_LOOP_199_5_VITIS_LOOP_200_6>
<Slack>7.30</Slack>
<TripCount>100</TripCount>
<Latency>100</Latency>
<AbsoluteTimeLatency>1000</AbsoluteTimeLatency>
<PipelineII>1</PipelineII>
<PipelineDepth>2</PipelineDepth>
<InstanceList>
</InstanceList>
</VITIS_LOOP_199_5_VITIS_LOOP_200_6>
</SummaryOfLoopLatency>
</PerformanceEstimates>

<AreaEstimates>
<Resources>
<FF>25</FF>
<LUT>178</LUT>
<BRAM_18K>0</BRAM_18K>
<DSP>0</DSP>
<URAM>0</URAM>
</Resources>
<AvailableResources>
<BRAM_18K>4032</BRAM_18K>
<DSP>9216</DSP>
<FF>2592000</FF>
<LUT>1296000</LUT>
<URAM>960</URAM>
</AvailableResources>
</AreaEstimates>

<InterfaceSummary>
<RtlPorts>
<name>ap_clk</name>
<Object>naive_findClustersHLS1_Pipeline_VITIS_LOOP_199_5_VITIS_LOOP_200_6</Object>
<Type>return value</Type>
<Scope></Scope>
<IOProtocol>ap_ctrl_hs</IOProtocol>
<IOConfig></IOConfig>
<Dir>in</Dir>
<Bits>1</Bits>
<Attribute>control</Attribute>
</RtlPorts>
<RtlPorts>
<name>ap_rst</name>
<Object>naive_findClustersHLS1_Pipeline_VITIS_LOOP_199_5_VITIS_LOOP_200_6</Object>
<Type>return value</Type>
<Scope></Scope>
<IOProtocol>ap_ctrl_hs</IOProtocol>
<IOConfig></IOConfig>
<Dir>in</Dir>
<Bits>1</Bits>
<Attribute>control</Attribute>
</RtlPorts>
<RtlPorts>
<name>ap_start</name>
<Object>naive_findClustersHLS1_Pipeline_VITIS_LOOP_199_5_VITIS_LOOP_200_6</Object>
<Type>return value</Type>
<Scope></Scope>
<IOProtocol>ap_ctrl_hs</IOProtocol>
<IOConfig></IOConfig>
<Dir>in</Dir>
<Bits>1</Bits>
<Attribute>control</Attribute>
</RtlPorts>
<RtlPorts>
<name>ap_done</name>
<Object>naive_findClustersHLS1_Pipeline_VITIS_LOOP_199_5_VITIS_LOOP_200_6</Object>
<Type>return value</Type>
<Scope></Scope>
<IOProtocol>ap_ctrl_hs</IOProtocol>
<IOConfig></IOConfig>
<Dir>out</Dir>
<Bits>1</Bits>
<Attribute>control</Attribute>
</RtlPorts>
<RtlPorts>
<name>ap_idle</name>
<Object>naive_findClustersHLS1_Pipeline_VITIS_LOOP_199_5_VITIS_LOOP_200_6</Object>
<Type>return value</Type>
<Scope></Scope>
<IOProtocol>ap_ctrl_hs</IOProtocol>
<IOConfig></IOConfig>
<Dir>out</Dir>
<Bits>1</Bits>
<Attribute>control</Attribute>
</RtlPorts>
<RtlPorts>
<name>ap_ready</name>
<Object>naive_findClustersHLS1_Pipeline_VITIS_LOOP_199_5_VITIS_LOOP_200_6</Object>
<Type>return value</Type>
<Scope></Scope>
<IOProtocol>ap_ctrl_hs</IOProtocol>
<IOConfig></IOConfig>
<Dir>out</Dir>
<Bits>1</Bits>
<Attribute>control</Attribute>
</RtlPorts>
<RtlPorts>
<name>clusterArray_x_address0</name>
<Object>clusterArray_x</Object>
<Type>array</Type>
<Scope></Scope>
<IOProtocol>ap_memory</IOProtocol>
<IOConfig></IOConfig>
<Dir>out</Dir>
<Bits>7</Bits>
<Attribute>address</Attribute>
</RtlPorts>
<RtlPorts>
<name>clusterArray_x_ce0</name>
<Object>clusterArray_x</Object>
<Type>array</Type>
<Scope></Scope>
<IOProtocol>ap_memory</IOProtocol>
<IOConfig></IOConfig>
<Dir>out</Dir>
<Bits>1</Bits>
<Attribute>control</Attribute>
</RtlPorts>
<RtlPorts>
<name>clusterArray_x_we0</name>
<Object>clusterArray_x</Object>
<Type>array</Type>
<Scope></Scope>
<IOProtocol>ap_memory</IOProtocol>
<IOConfig></IOConfig>
<Dir>out</Dir>
<Bits>1</Bits>
<Attribute>control</Attribute>
</RtlPorts>
<RtlPorts>
<name>clusterArray_x_d0</name>
<Object>clusterArray_x</Object>
<Type>array</Type>
<Scope></Scope>
<IOProtocol>ap_memory</IOProtocol>
<IOConfig></IOConfig>
<Dir>out</Dir>
<Bits>32</Bits>
<Attribute>data</Attribute>
</RtlPorts>
<RtlPorts>
<name>clusterArray_y_address0</name>
<Object>clusterArray_y</Object>
<Type>array</Type>
<Scope></Scope>
<IOProtocol>ap_memory</IOProtocol>
<IOConfig></IOConfig>
<Dir>out</Dir>
<Bits>7</Bits>
<Attribute>address</Attribute>
</RtlPorts>
<RtlPorts>
<name>clusterArray_y_ce0</name>
<Object>clusterArray_y</Object>
<Type>array</Type>
<Scope></Scope>
<IOProtocol>ap_memory</IOProtocol>
<IOConfig></IOConfig>
<Dir>out</Dir>
<Bits>1</Bits>
<Attribute>control</Attribute>
</RtlPorts>
<RtlPorts>
<name>clusterArray_y_we0</name>
<Object>clusterArray_y</Object>
<Type>array</Type>
<Scope></Scope>
<IOProtocol>ap_memory</IOProtocol>
<IOConfig></IOConfig>
<Dir>out</Dir>
<Bits>1</Bits>
<Attribute>control</Attribute>
</RtlPorts>
<RtlPorts>
<name>clusterArray_y_d0</name>
<Object>clusterArray_y</Object>
<Type>array</Type>
<Scope></Scope>
<IOProtocol>ap_memory</IOProtocol>
<IOConfig></IOConfig>
<Dir>out</Dir>
<Bits>32</Bits>
<Attribute>data</Attribute>
</RtlPorts>
<RtlPorts>
<name>clusterArray_clusterID_address0</name>
<Object>clusterArray_clusterID</Object>
<Type>array</Type>
<Scope></Scope>
<IOProtocol>ap_memory</IOProtocol>
<IOConfig></IOConfig>
<Dir>out</Dir>
<Bits>7</Bits>
<Attribute>address</Attribute>
</RtlPorts>
<RtlPorts>
<name>clusterArray_clusterID_ce0</name>
<Object>clusterArray_clusterID</Object>
<Type>array</Type>
<Scope></Scope>
<IOProtocol>ap_memory</IOProtocol>
<IOConfig></IOConfig>
<Dir>out</Dir>
<Bits>1</Bits>
<Attribute>control</Attribute>
</RtlPorts>
<RtlPorts>
<name>clusterArray_clusterID_we0</name>
<Object>clusterArray_clusterID</Object>
<Type>array</Type>
<Scope></Scope>
<IOProtocol>ap_memory</IOProtocol>
<IOConfig></IOConfig>
<Dir>out</Dir>
<Bits>1</Bits>
<Attribute>control</Attribute>
</RtlPorts>
<RtlPorts>
<name>clusterArray_clusterID_d0</name>
<Object>clusterArray_clusterID</Object>
<Type>array</Type>
<Scope></Scope>
<IOProtocol>ap_memory</IOProtocol>
<IOConfig></IOConfig>
<Dir>out</Dir>
<Bits>32</Bits>
<Attribute>data</Attribute>
</RtlPorts>
<RtlPorts>
<name>clusterGrid_x_address0</name>
<Object>clusterGrid_x</Object>
<Type>array</Type>
<Scope></Scope>
<IOProtocol>ap_memory</IOProtocol>
<IOConfig></IOConfig>
<Dir>out</Dir>
<Bits>7</Bits>
<Attribute>address</Attribute>
</RtlPorts>
<RtlPorts>
<name>clusterGrid_x_ce0</name>
<Object>clusterGrid_x</Object>
<Type>array</Type>
<Scope></Scope>
<IOProtocol>ap_memory</IOProtocol>
<IOConfig></IOConfig>
<Dir>out</Dir>
<Bits>1</Bits>
<Attribute>control</Attribute>
</RtlPorts>
<RtlPorts>
<name>clusterGrid_x_q0</name>
<Object>clusterGrid_x</Object>
<Type>array</Type>
<Scope></Scope>
<IOProtocol>ap_memory</IOProtocol>
<IOConfig></IOConfig>
<Dir>in</Dir>
<Bits>32</Bits>
<Attribute>data</Attribute>
</RtlPorts>
<RtlPorts>
<name>clusterGrid_y_address0</name>
<Object>clusterGrid_y</Object>
<Type>array</Type>
<Scope></Scope>
<IOProtocol>ap_memory</IOProtocol>
<IOConfig></IOConfig>
<Dir>out</Dir>
<Bits>7</Bits>
<Attribute>address</Attribute>
</RtlPorts>
<RtlPorts>
<name>clusterGrid_y_ce0</name>
<Object>clusterGrid_y</Object>
<Type>array</Type>
<Scope></Scope>
<IOProtocol>ap_memory</IOProtocol>
<IOConfig></IOConfig>
<Dir>out</Dir>
<Bits>1</Bits>
<Attribute>control</Attribute>
</RtlPorts>
<RtlPorts>
<name>clusterGrid_y_q0</name>
<Object>clusterGrid_y</Object>
<Type>array</Type>
<Scope></Scope>
<IOProtocol>ap_memory</IOProtocol>
<IOConfig></IOConfig>
<Dir>in</Dir>
<Bits>32</Bits>
<Attribute>data</Attribute>
</RtlPorts>
<RtlPorts>
<name>clusterGrid_clusterID_address0</name>
<Object>clusterGrid_clusterID</Object>
<Type>array</Type>
<Scope></Scope>
<IOProtocol>ap_memory</IOProtocol>
<IOConfig></IOConfig>
<Dir>out</Dir>
<Bits>7</Bits>
<Attribute>address</Attribute>
</RtlPorts>
<RtlPorts>
<name>clusterGrid_clusterID_ce0</name>
<Object>clusterGrid_clusterID</Object>
<Type>array</Type>
<Scope></Scope>
<IOProtocol>ap_memory</IOProtocol>
<IOConfig></IOConfig>
<Dir>out</Dir>
<Bits>1</Bits>
<Attribute>control</Attribute>
</RtlPorts>
<RtlPorts>
<name>clusterGrid_clusterID_q0</name>
<Object>clusterGrid_clusterID</Object>
<Type>array</Type>
<Scope></Scope>
<IOProtocol>ap_memory</IOProtocol>
<IOConfig></IOConfig>
<Dir>in</Dir>
<Bits>32</Bits>
<Attribute>data</Attribute>
</RtlPorts>
</InterfaceSummary>

</profile>
